LICENSE
MANIFEST.in
Readme.rst
requirements.txt
setup.cfg
setup.py
platform_utility.egg-info/PKG-INFO
platform_utility.egg-info/SOURCES.txt
platform_utility.egg-info/dependency_links.txt
platform_utility.egg-info/top_level.txt
utilitylibrary/__init__.py
utilitylibrary/unique.py
utilitylibrary/upload.py
utilitylibrary/utility.py